{
  "$schema": "https://developer.microsoft.com/json-schemas/fabric/item/report/definition/visualContainer/2.7.0/schema.json",
  "name": "da745474383089b7365a",
  "position": {
    "x": 18.22784810126582,
    "y": 380.75949367088606,
    "z": 15000,
    "height": 34.430379746835442,
    "width": 42.531645569620252,
    "tabOrder": 13000
  },
  "visual": {
    "visualType": "image",
    "objects": {
      "general": [
        {
          "properties": {
            "imageUrl": {
              "expr": {
                "ResourcePackageItem": {
                  "PackageName": "RegisteredResources",
                  "PackageType": 1,
                  "ItemName": "filter7055903506484018.png"
                }
              }
            }
          }
        }
      ]
    },
    "visualContainerObjects": {
      "visualLink": [
        {
          "properties": {
            "show": {
              "expr": {
                "Literal": {
                  "Value": "true"
                }
              }
            },
            "type": {
              "expr": {
                "Literal": {
                  "Value": "'Bookmark'"
                }
              }
            },
            "bookmark": {
              "expr": {
                "Literal": {
                  "Value": "'0714c4212ce3ea3cf96e'"
                }
              }
            }
          }
        }
      ],
      "title": [
        {
          "properties": {
            "text": {
              "expr": {
                "Literal": {
                  "Value": "'Botão Filtros'"
                }
              }
            }
          }
        }
      ]
    },
    "drillFilterOtherVisuals": true
  },
  "howCreated": "InsertVisualButton"
}