{
  "$schema": "https://developer.microsoft.com/json-schemas/fabric/item/report/definition/visualContainer/2.7.0/schema.json",
  "name": "262651ac98c32982ee39",
  "position": {
    "x": 95.0943396226415,
    "y": 19.0188679245283,
    "z": 0,
    "height": 107.32075471698113,
    "width": 1704.9056603773583,
    "tabOrder": 14000
  },
  "visual": {
    "visualType": "shape",
    "objects": {
      "shape": [
        {
          "properties": {
            "tileShape": {
              "expr": {
                "Literal": {
                  "Value": "'line'"
                }
              }
            }
          }
        }
      ],
      "rotation": [
        {
          "properties": {
            "shapeAngle": {
              "expr": {
                "Literal": {
                  "Value": "0L"
                }
              }
            }
          }
        }
      ],
      "fill": [
        {
          "properties": {
            "fillColor": {
              "solid": {
                "color": {
                  "expr": {
                    "Literal": {
                      "Value": "'#1DA1F2'"
                    }
                  }
                }
              }
            }
          },
          "selector": {
            "id": "default"
          }
        }
      ]
    },
    "drillFilterOtherVisuals": true
  },
  "howCreated": "InsertVisualButton"
}