{
  "$schema": "https://developer.microsoft.com/json-schemas/fabric/item/report/definition/visualContainer/2.6.0/schema.json",
  "name": "87464b19f834cef448e8",
  "position": {
    "x": 2.2290183931642784,
    "y": 14.140304763879257,
    "z": 2000,
    "height": 33.278443113772454,
    "width": 79.3562874251497,
    "tabOrder": 0
  },
  "visual": {
    "visualType": "textbox",
    "objects": {
      "general": [
        {
          "properties": {
            "paragraphs": [
              {
                "textRuns": [
                  {
                    "value": "Resposta",
                    "textStyle": {
                      "fontSize": "12pt",
                      "color": "#ffffff"
                    }
                  }
                ],
                "horizontalTextAlignment": "center"
              }
            ]
          }
        }
      ]
    },
    "visualContainerObjects": {
      "background": [
        {
          "properties": {
            "color": {
              "solid": {
                "color": {
                  "expr": {
                    "Literal": {
                      "Value": "'#0097B2'"
                    }
                  }
                }
              }
            }
          }
        }
      ]
    },
    "drillFilterOtherVisuals": true
  },
  "parentGroupName": "6760d4a26b0d6fc0218b"
}